nndesg/__init__.py
nndesg-0.1.1.dist-info/LICENSE
nndesg-0.1.1.dist-info/METADATA
nndesg-0.1.1.dist-info/WHEEL
nndesg-0.1.1.dist-info/RECORD
