Metadata-Version: 2.1
Name: nndesg
Version: 0.1.1
Summary: PyTorch implementation of Neural Network Design (Second Edition).
License: MIT
Author: Cylix Lee
Author-email: cylix.lee@outlook.com
Requires-Python: >=3.8,<4.0
Classifier: Development Status :: 3 - Alpha
Classifier: Intended Audience :: Developers
Classifier: License :: OSI Approved :: MIT License
Classifier: Programming Language :: Python :: 3
Classifier: Programming Language :: Python :: 3.8
Classifier: Programming Language :: Python :: 3.9
Classifier: Programming Language :: Python :: 3.10
Classifier: Programming Language :: Python :: 3.11
Classifier: Programming Language :: Python :: 3.12
Classifier: Topic :: Scientific/Engineering :: Artificial Intelligence
Requires-Dist: torch (>=2.4.0,<3.0.0)
